akeoott_logging_config/__init__.py
akeoott_logging_config/logging_config.py
akeoott_logging_config-1.2.1.dist-info/licenses/LICENCE
akeoott_logging_config-1.2.1.dist-info/METADATA
akeoott_logging_config-1.2.1.dist-info/WHEEL
akeoott_logging_config-1.2.1.dist-info/top_level.txt
akeoott_logging_config-1.2.1.dist-info/RECORD
