Metadata-Version: 2.4
Name: akeoott_logging_config
Version: 1.2.1
Summary: A simple yet robust logging configuration library for Python applications.
Author-email: Akeoott <amejanin00@gmail.com>
Project-URL: Homepage, https://github.com/Akeoottt/akeoott-logging-config
Project-URL: Issues, https://github.com/Akeoottt/akeoott-logging-config/issues
Keywords: logging,log,configuration,library,utility,preset,python
Classifier: Programming Language :: Python :: 3
Classifier: Programming Language :: Python :: 3.8
Classifier: Programming Language :: Python :: 3.9
Classifier: Programming Language :: Python :: 3.10
Classifier: Programming Language :: Python :: 3.11
Classifier: Programming Language :: Python :: 3.12
Classifier: License :: OSI Approved :: GNU Lesser General Public License v3 (LGPLv3)
Classifier: Operating System :: OS Independent
Classifier: Development Status :: 5 - Production/Stable
Classifier: Topic :: Software Development :: Libraries :: Python Modules
Classifier: Topic :: System :: Logging
Requires-Python: >=3.8
License-File: LICENCE
Dynamic: license-file
